{"success":true,"source":"xp2csv.pl","last_updated":"2014/02/20 16:16:00 UTC"
,"type":1,"icao":"8G1","name":"Willard","lat":41.03875,"lon":-82.7245655,"rwys":1,"ils":0,"elev":967,"index":1597633,"path":"w090n40/w083n41"
,"runways":[
{"len_m":1227,"wid_m":19.81,"hdg":97,"surf":"Asphalt","rwy1":"10","lat1":41.03946700,"lon1":-82.73180300,"rwy2":"28","lat2":41.03803300,"lon2":-82.71732800}
]
,"helipads":[
]
,"radios":[
{"type":"CTAF","freq":122.9,"desc":"CTAF"},
{"type":"APP","freq":124.2,"desc":"MANSFIELD APP/DEP"}
]
,"ils":[
]
}
