{"success":true,"source":"xp2csv.pl","last_updated":"2014/02/20 16:16:00 UTC"
,"type":1,"icao":"LTAK","name":"Iskenderun","lat":36.573472,"lon":36.154,"rwys":1,"ils":0,"elev":25,"index":3547040,"path":"e030n30/e036n36"
,"runways":[
{"len_m":1162,"wid_m":29.87,"hdg":67,"surf":"Asphalt","rwy1":"07","lat1":36.57150000,"lon1":36.14798600,"rwy2":"25","lat2":36.57544400,"lon2":36.16001400}
]
,"helipads":[
]
,"radios":[
{"type":"APP","freq":118,"desc":"INCIRLIK APP"},
{"type":"APP","freq":126.5,"desc":"INCIRLIK APP"}
]
,"ils":[
]
}
