{"success":true,"source":"xp2csv.pl","last_updated":"2014/02/20 16:16:00 UTC"
,"type":1,"icao":"ZSPD","name":"Pudong","lat":31.1434265,"lon":121.80509225,"rwys":2,"ils":4,"elev":13,"index":4939339,"path":"e120n30/e121n31"
,"runways":[
{"len_m":3998,"wid_m":60.05,"hdg":162,"surf":"Concrete","rwy1":"17","lat1":31.16128900,"lon1":121.78588900,"rwy2":"35","lat2":31.12698600,"lon2":121.79883900},
{"len_m":3799,"wid_m":60.05,"hdg":162,"surf":"Concrete","rwy1":"16","lat1":31.15901400,"lon1":121.81166900,"rwy2":"34","lat2":31.12641700,"lon2":121.82397200}
]
,"helipads":[
]
,"radios":[
{"type":"ATIS","freq":127.85,"desc":"ATIS"},
{"type":"CLD","freq":121.95,"desc":"DEL"},
{"type":"CLD","freq":121.7,"desc":"DEL"},
{"type":"GND","freq":121.8,"desc":"GND EAST"},
{"type":"GND","freq":121.7,"desc":"GND EAST"},
{"type":"GND","freq":121.65,"desc":"GND WEST"},
{"type":"TWR","freq":118.4,"desc":"TWR EAST"},
{"type":"TWR","freq":124.35,"desc":"TWR EAST"},
{"type":"TWR","freq":118.8,"desc":"TWR WEST"},
{"type":"APP","freq":121.3,"desc":"SHAINGHAI APP SCTR 3"},
{"type":"APP","freq":119.2,"desc":"SHAINGHAI APP SCTR 3"},
{"type":"APP","freq":120.3,"desc":"SHANGHAI APP SCTR 1"},
{"type":"APP","freq":119.75,"desc":"SHANGHAI APP SCTR 2"},
{"type":"APP","freq":120.8,"desc":"SHANGHAI APP SCTR 2"},
{"type":"APP","freq":123.8,"desc":"SHANGHAI APP SCRT 4"}
]
,"ils":[
{"type":"ILS","freq":108.7,"lat":31.12395000,"lon":121.82491900,"rng_nm":18,"alt_fmsl":12,"hdg":162.08,"id":"IZZ","rwy":"16","desc":"ILS-cat-I"},
{"type":"ILS","freq":110.7,"lat":31.12300800,"lon":121.79953900,"rng_nm":18,"alt_fmsl":11,"hdg":163.03,"id":"IPD","rwy":"17","desc":"ILS-cat-II"},
{"type":"ILS","freq":108.3,"lat":31.16148100,"lon":121.81072200,"rng_nm":18,"alt_fmsl":12,"hdg":342.07,"id":"IDD","rwy":"34","desc":"ILS-cat-I"},
{"type":"ILS","freq":111.9,"lat":31.16258900,"lon":121.78519200,"rng_nm":18,"alt_fmsl":11,"hdg":341.83,"id":"INN","rwy":"35","desc":"ILS-cat-II"},
{"type":"GS","freq":108.7,"lat":31.15669200,"lon":121.81399700,"rng_nm":10,"alt_fmsl":12,"id":"IZZ","rwy":"16","desc":"GS","gs":3},
{"type":"GS","freq":110.7,"lat":31.15697500,"lon":121.78530000,"rng_nm":10,"alt_fmsl":11,"id":"IPD","rwy":"17","desc":"GS","gs":3},
{"type":"GS","freq":108.3,"lat":31.12947500,"lon":121.82423600,"rng_nm":10,"alt_fmsl":12,"id":"IDD","rwy":"34","desc":"GS","gs":3},
{"type":"GS","freq":111.9,"lat":31.12809400,"lon":121.79677500,"rng_nm":10,"alt_fmsl":11,"id":"INN","rwy":"35","desc":"GS","gs":3},
{"type":"OM","freq":0,"lat":31.04666100,"lon":121.82001100,"rng_nm":0,"alt_fmsl":13,"id":"----","rwy":"35","desc":"OM"},
{"type":"MM","freq":0,"lat":31.16800600,"lon":121.80821400,"rng_nm":0,"alt_fmsl":13,"id":"----","rwy":"16","desc":"MM"},
{"type":"MM","freq":0,"lat":31.16833300,"lon":121.78000000,"rng_nm":0,"alt_fmsl":13,"id":"----","rwy":"17","desc":"MM"},
{"type":"MM","freq":0,"lat":31.11742500,"lon":121.82742800,"rng_nm":0,"alt_fmsl":13,"id":"----","rwy":"34","desc":"MM"},
{"type":"IM","freq":0,"lat":31.16201100,"lon":121.81051700,"rng_nm":0,"alt_fmsl":13,"id":"----","rwy":"16","desc":"IM"},
{"type":"IM","freq":0,"lat":31.16274700,"lon":121.78515000,"rng_nm":0,"alt_fmsl":11,"id":"----","rwy":"17","desc":"IM"},
{"type":"IM","freq":0,"lat":31.12341900,"lon":121.82512500,"rng_nm":0,"alt_fmsl":13,"id":"----","rwy":"34","desc":"IM"},
{"type":"IM","freq":0,"lat":31.12285000,"lon":121.79958300,"rng_nm":0,"alt_fmsl":11,"id":"----","rwy":"35","desc":"IM"},
{"type":"DME","freq":108.7,"lat":31.15669200,"lon":121.81399700,"rng_nm":18,"alt_fmsl":12,"id":"IZZ","rwy":"16","desc":"DME-ILS"},
{"type":"DME","freq":110.7,"lat":31.15697500,"lon":121.78530000,"rng_nm":18,"alt_fmsl":11,"id":"IPD","rwy":"17","desc":"DME-ILS"},
{"type":"DME","freq":108.3,"lat":31.12947500,"lon":121.82423600,"rng_nm":18,"alt_fmsl":12,"id":"IDD","rwy":"34","desc":"DME-ILS"}
]
}
