{"success":true,"source":"xp2csv.pl","last_updated":"2014/02/20 16:16:00 UTC"
,"type":1,"icao":"ZSQD","name":"Liuting","lat":36.266107,"lon":120.3744345,"rwys":1,"ils":2,"elev":33,"index":4923281,"path":"e120n30/e120n36"
,"runways":[
{"len_m":3409,"wid_m":45.11,"hdg":165,"surf":"Concrete","rwy1":"17","lat1":36.28098600,"lon1":120.36970000,"rwy2":"35","lat2":36.25122800,"lon2":120.37916900}
]
,"helipads":[
]
,"radios":[
{"type":"ATIS","freq":127.2,"desc":"ATIS"},
{"type":"GND","freq":121.65,"desc":"QINGDAO GND"},
{"type":"TWR","freq":118.7,"desc":"QINGDAO TWR"},
{"type":"TWR","freq":124.3,"desc":"QINGDAO TWR"},
{"type":"APP","freq":119.4,"desc":"QINGDAO"},
{"type":"APP","freq":124.6,"desc":"QINGDAO"}
]
,"ils":[
{"type":"ILS","freq":110.7,"lat":36.24866400,"lon":120.38003900,"rng_nm":18,"alt_fmsl":33,"hdg":165.54,"id":"INX","rwy":"17","desc":"ILS-cat-I"},
{"type":"ILS","freq":111.7,"lat":36.28350600,"lon":120.36884400,"rng_nm":18,"alt_fmsl":33,"hdg":345.54,"id":"IPP","rwy":"35","desc":"ILS-cat-I"},
{"type":"GS","freq":110.7,"lat":36.27799700,"lon":120.36933100,"rng_nm":10,"alt_fmsl":33,"id":"INX","rwy":"17","desc":"GS","gs":3},
{"type":"GS","freq":111.7,"lat":36.25360800,"lon":120.37697800,"rng_nm":10,"alt_fmsl":33,"id":"IPP","rwy":"35","desc":"GS","gs":3},
{"type":"OM","freq":0,"lat":36.19645600,"lon":120.39774700,"rng_nm":0,"alt_fmsl":33,"id":"----","rwy":"35","desc":"OM"},
{"type":"MM","freq":0,"lat":36.28889400,"lon":120.36701400,"rng_nm":0,"alt_fmsl":33,"id":"----","rwy":"17","desc":"MM"},
{"type":"MM","freq":0,"lat":36.24080000,"lon":120.38270800,"rng_nm":0,"alt_fmsl":33,"id":"----","rwy":"35","desc":"MM"},
{"type":"DME","freq":110.7,"lat":36.27799700,"lon":120.36933100,"rng_nm":18,"alt_fmsl":33,"id":"INX","rwy":"17","desc":"DME-ILS"}
]
}
