{"success":true,"source":"xp2csv.pl","last_updated":"2014/02/20 16:16:00 UTC"
,"type":1,"icao":"II35","name":"Lindley - Private","lat":39.80865611,"lon":-86.49555417,"rwys":2,"ils":0,"elev":925,"index":1532018,"path":"w090n30/w087n39"
,"runways":[
{"len_m":791,"wid_m":22.86,"hdg":357,"surf":"Turf/grass","rwy1":"36","lat1":39.80509241,"lon1":-86.49539217,"rwy2":"18","lat2":39.81221981,"lon2":-86.49571617},
{"len_m":611,"wid_m":20.12,"hdg":88,"surf":"Turf/grass","rwy1":"09","lat1":39.80856038,"lon1":-86.49912272,"rwy2":"27","lat2":39.80875184,"lon2":-86.49198562}
]
,"helipads":[
]
,"radios":[
]
,"ils":[
]
}
