{"success":true,"source":"xp2csv.pl","last_updated":"2013/12/07 11:07:17 UTC"
,"type":1,"icao":"4NE1","name":"Mc Millan Ranch","lat":41.75350177,"lon":-099.76129853,"rwys":2,"ils":0,"index":1319152,"path":"w100n40/w100n41"
,"runways":[
{"len_m":1062,"wid_m":17.98,"hdg":91,"surf":"Turf/grass","rwy1":"08","lat1":41.75389933,"lon1":-99.76057724,"rwy2":"26","lat2":41.75369700,"lon2":-99.74780000},
{"len_m":798,"wid_m":25.91,"hdg":131,"surf":"Turf/grass","rwy1":"12","lat1":41.75433515,"lon1":-99.76175599,"rwy2":"30","lat2":41.74959084,"lon2":-99.75453709}
]
,"helipads":[
]
,"radios":[
]
}
