{"success":true,"source":"xp2csv.pl","last_updated":"2013/12/07 11:07:17 UTC"
,"type":1,"icao":"8Q0","name":"Travis Lrrs Aero Club","lat":38.26935694,"lon":-121.97524278,"rwys":2,"ils":0,"index":958480,"path":"w130n30/w122n38"
,"runways":[
{"len_m":610,"wid_m":12.19,"hdg":56,"surf":"Asphalt","rwy1":"04","lat1":38.26782308,"lon1":-121.97813924,"rwy2":"22","lat2":38.27089080,"lon2":-121.97234632},
{"len_m":548,"wid_m":12.19,"hdg":175,"surf":"Turf/grass","rwy1":"16","lat1":38.27181961,"lon1":-121.97546212,"rwy2":"34","lat2":38.26689427,"lon2":-121.97502344}
]
,"helipads":[
]
,"radios":[
]
}
