{"success":true,"source":"xp2csv.pl","last_updated":"2013/12/07 11:07:17 UTC"
,"type":1,"icao":"KPSN","name":"Palestine Muni","lat":31.77942725,"lon":-95.70630275,"rwys":2,"ils":0,"index":1384049,"path":"w100n30/w096n31"
,"runways":[
{"len_m":1525,"wid_m":30.48,"hdg":180,"surf":"Asphalt","rwy1":"18","lat1":31.78871400,"lon1":-95.70626400,"rwy2":"36","lat2":31.77495300,"lon2":-95.70641100},
{"len_m":1220,"wid_m":22.86,"hdg":90,"surf":"Asphalt","rwy1":"09","lat1":31.77707500,"lon1":-95.71270800,"rwy2":"27","lat2":31.77696700,"lon2":-95.69982800}
]
,"helipads":[
]
,"radios":[
{"type":"ATIS","freq":118.02,"desc":"AWOS 3"},
{"type":"CTAF","freq":122.7,"desc":"CTAF/UNICOM"},
{"type":"APP","freq":135.25,"desc":"FORT WORTH CNTR"}
]
}
