{"success":true,"source":"xp2json.pl","last_updated":"2013/12/11 18:57:44 UTC"
,"type":1,"icao":"LFRU","name":"Morlaix Ploujean","lat":48.59999100,"lon":-3.81659900,"rwys":1,"ils":1,"index":2892448,"path":"w010n40/w004n48"
,"runways":[
{"len_m":1616,"wid_m":36.88,"hdg":40,"surf":"Asphalt","rwy1":"04","lat1":48.59767600,"lon1":-3.82291400,"rwy2":"22","lat2":48.60880000,"lon2":-3.80879800}
]
,"helipads":[
]
,"radios":[
{"type":"ATIS","freq":118.5,"desc":"MORLAIX FSS"},
{"type":"CTAF","freq":118.5,"desc":"MORLAIX MULT"},
{"type":"APP","freq":135.82,"desc":"IROISE APP"},
{"type":"APP","freq":122.4,"desc":"LANDI APP"}
]
}
