{"success":true,"source":"xp2csv.pl","last_updated":"2013/12/07 11:07:17 UTC"
,"type":1,"icao":"LIMB","name":"Bresso","lat":45.53872500,"lon":009.19911500,"rwys":1,"ils":0,"index":3105248,"path":"e000n40/e009n45"
,"runways":[
{"len_m":1082,"wid_m":29.87,"hdg":179,"surf":"Asphalt","rwy1":"18","lat1":45.54515800,"lon1":9.20226700,"rwy2":"36","lat2":45.53541700,"lon2":9.20233300}
]
,"helipads":[
{"rwy1":"H1","len_m":30,"wid_m":30.48,"hdg":9,"surf":"Concrete","lat1":45.53784500,"lon1":9.20336900}
]
,"radios":[
]
}
