{"success":true,"source":"xp2json.pl","last_updated":"2013/12/11 18:57:44 UTC"
,"type":1,"icao":"MUCL","name":"Vilo Acuna Intl","lat":21.62269400,"lon":-81.55541990,"rwys":1,"ils":0,"index":1612771,"path":"w090n20/w082n21"
,"runways":[
{"len_m":3008,"wid_m":45.11,"hdg":116,"surf":"Asphalt","rwy1":"12","lat1":21.62241400,"lon1":-81.55905300,"rwy2":"30","lat2":21.61048900,"lon2":-81.53294700}
]
,"helipads":[
]
,"radios":[
{"type":"TWR","freq":118.5,"desc":"CAYO LARGO TWR"},
{"type":"APP","freq":120.1,"desc":"CAYO LARGO APP"}
]
}
