{"success":true,"source":"xp2csv.pl","last_updated":"2013/12/07 11:07:17 UTC"
,"type":1,"icao":"YCRK","name":"Christmas Creek Stn","lat":-18.87881729,"lon":125.92371342,"rwys":2,"ils":0,"index":5001671,"path":"e120s20/e125s19"
,"runways":[
{"len_m":1309,"wid_m":170.08,"hdg":147,"surf":"Dirt","rwy1":"14","lat1":-18.87391933,"lon1":125.92573633,"rwy2":"32","lat2":-18.88390239,"lon2":125.93239727},
{"len_m":1868,"wid_m":157.89,"hdg":74,"surf":"Dirt","rwy1":"7","lat1":-18.87498883,"lon1":125.92547878,"rwy2":"25","lat2":-18.87046161,"lon2":125.94256043}
]
,"helipads":[
]
,"radios":[
]
}
