{"success":true,"source":"xp2csv.pl","last_updated":"2014/02/20 16:16:00 UTC"
,"type":1,"icao":"SFDH","name":"Dunnose Head","lat":-51.75318033,"lon":-60.41601179,"rwys":3,"ils":0,"elev":41,"index":1952138,"path":"w070s60/w061s52"
,"runways":[
{"len_m":576,"wid_m":29.87,"hdg":67,"surf":"Turf/grass","rwy1":"07","lat1":-51.75446504,"lon1":-60.42062624,"rwy2":"25","lat2":-51.75251192,"lon2":-60.41290054},
{"len_m":362,"wid_m":29.87,"hdg":113,"surf":"Turf/grass","rwy1":"11","lat1":-51.75265344,"lon1":-60.41826707,"rwy2":"29","lat2":-51.75395330,"lon2":-60.41344865},
{"len_m":517,"wid_m":29.87,"hdg":204,"surf":"Turf/grass","rwy1":"02","lat1":-51.75063103,"lon1":-60.41386775,"rwy2":"20","lat2":-51.75486726,"lon2":-60.41696048}
]
,"helipads":[
]
,"radios":[
]
,"ils":[
]
}
